kalamine/__init__.py
kalamine/cli.py
kalamine/cli_msklc.py
kalamine/cli_xkb.py
kalamine/help.py
kalamine/layout.py
kalamine/msklc_manager.py
kalamine/server.py
kalamine/template.py
kalamine/utils.py
kalamine/xkb_manager.py
kalamine/data/dead_keys.yaml
kalamine/data/geometry.yaml
kalamine/data/key_sym.yaml
kalamine/data/layout.yaml
kalamine/data/qwerty_vk.yaml
kalamine/data/scan_codes.yaml
kalamine/data/user_guide.yaml
kalamine/data/win_locales.yaml
kalamine/generators/__init.py__
kalamine/generators/ahk.py
kalamine/generators/keylayout.py
kalamine/generators/klc.py
kalamine/generators/web.py
kalamine/generators/xkb.py
kalamine/templates/base.C
kalamine/templates/base.ahk
kalamine/templates/base.keylayout
kalamine/templates/base.klc
kalamine/templates/base.xkb_keymap
kalamine/templates/base.xkb_symbols
kalamine/templates/full.C
kalamine/templates/full.RC
kalamine/templates/full.ahk
kalamine/templates/full.keylayout
kalamine/templates/full.klc
kalamine/templates/full.xkb_keymap
kalamine/templates/full.xkb_symbols
kalamine/templates/full_1dk.xkb_keymap
kalamine/templates/full_1dk.xkb_symbols
kalamine/templates/x-keyboard.svg
kalamine/www/demo.js
kalamine/www/style.css
kalamine/www/x-keyboard.js
kalamine-0.38.dist-info/METADATA
kalamine-0.38.dist-info/WHEEL
kalamine-0.38.dist-info/entry_points.txt
kalamine-0.38.dist-info/licenses/LICENSE
kalamine-0.38.dist-info/RECORD
